pyProjExample/__init__.py
pyProjExample/mult.py
pyprojexample-0.1.0.dist-info/LICENSE
pyprojexample-0.1.0.dist-info/METADATA
pyprojexample-0.1.0.dist-info/WHEEL
pyprojexample-0.1.0.dist-info/RECORD
