Metadata-Version: 2.1
Name: pyprojexample
Version: 0.1.0
Summary: 
Author: Richard Bell
Author-email: rcbell@eng.ucsd.edu
Requires-Python: >=3.8,<4.0
Classifier: Programming Language :: Python :: 3
Classifier: Programming Language :: Python :: 3.8
Classifier: Programming Language :: Python :: 3.9
Classifier: Programming Language :: Python :: 3.10
Classifier: Programming Language :: Python :: 3.11
Requires-Dist: numpy (>=1.24.2,<2.0.0)
Requires-Dist: pre-commit (>=3.1.0,<4.0.0)
Requires-Dist: pytest (>=7.2.1,<8.0.0)
